imagenet_voice/__init__.py
imagenet_voice/imagenet_voice.py
imagenet_voice-0.51.1.data/scripts/__init__.py
imagenet_voice-0.51.1.dist-info/METADATA
imagenet_voice-0.51.1.dist-info/WHEEL
imagenet_voice-0.51.1.dist-info/top_level.txt
imagenet_voice-0.51.1.dist-info/RECORD
