Metadata-Version: 2.1
Name: imagenet-voice
Version: 0.51.1
Summary: A collection of synthetic audio files containing spoken labels from ImageNet
Home-page: https://github.com/CharlesAverill/ImageNet-Voice/
Author: Charles Averill
Author-email: charlesaverill20@gmail.com
License: UNKNOWN
Platform: UNKNOWN
Classifier: Programming Language :: Python :: 3
Classifier: License :: OSI Approved :: MIT License
Classifier: Operating System :: OS Independent
Requires-Dist: progressbar2
Requires-Dist: wavio
Requires-Dist: numpy
